div3dfa/__init__.py
div3dfa/core.py
div3dfa-0.1.1.dist-info/METADATA
div3dfa-0.1.1.dist-info/WHEEL
div3dfa-0.1.1.dist-info/top_level.txt
div3dfa-0.1.1.dist-info/RECORD
