Metadata-Version: 2.4
Name: div3dfa
Version: 0.1.1
Summary: DFA implementation for checking binary strings with 1s divisible by 3
Author-email: Ahmed ElSany <ahmedelsany12@gmail.com>
License: MIT
Keywords: DFA,binary,divisible by 3,automata
Classifier: Programming Language :: Python :: 3
Classifier: License :: OSI Approved :: MIT License
Classifier: Operating System :: OS Independent
Requires-Python: >=3.8
